hippo/__init__.py
hippo/__main__.py
hippo/animal.py
hippo/apsw.py
hippo/chem.py
hippo/compound.py
hippo/cset.py
hippo/db.py
hippo/feature.py
hippo/fragalysis.py
hippo/interaction.py
hippo/iset.py
hippo/metadata.py
hippo/pca.py
hippo/plotting.py
hippo/pose.py
hippo/price.py
hippo/prolif.py
hippo/pset.py
hippo/pycule.py
hippo/pyvis.py
hippo/quote.py
hippo/reaction.py
hippo/recipe.py
hippo/rgen.py
hippo/rset.py
hippo/scoring.py
hippo/subsite.py
hippo/syndirella.py
hippo/tags.py
hippo/target.py
hippo/tools.py
hippo/web.py
hippo_db-0.3.38.dist-info/METADATA
hippo_db-0.3.38.dist-info/WHEEL
hippo_db-0.3.38.dist-info/licenses/LICENSE
hippo_db-0.3.38.dist-info/RECORD
