Metadata-Version: 2.4
Name: hippo-db
Version: 0.3.38
Summary: Hit Interaction Profiling and Procurement Optimisation
Project-URL: Homepage, https://hippo.winokan.com
Project-URL: Bug Tracker, https://github.com/mwinokan/HIPPO/issues
Author-email: Max Winokan <max@winokan.com>
License-File: LICENSE
Classifier: License :: OSI Approved :: MIT License
Classifier: Operating System :: OS Independent
Classifier: Programming Language :: Python :: 3
Requires-Python: >=3.10
Requires-Dist: apsw
Requires-Dist: chardet
Requires-Dist: hippo-plot
Requires-Dist: hirsch
Requires-Dist: ipywidgets
Requires-Dist: jupyterlab
Requires-Dist: molparse>=0.0.40
Requires-Dist: mpytools>=0.0.21
Requires-Dist: networkx
Requires-Dist: openmm
Requires-Dist: openpyxl
Requires-Dist: pandas
Requires-Dist: pycule
Requires-Dist: python-louvain
Requires-Dist: rdkit>=2024.9.6
Requires-Dist: scikit-learn
Requires-Dist: tqdm
Requires-Dist: yattag
